configmelt/__init__.py
configmelt/_routing.py
configmelt/_version.py
configmelt/configmelt.py
configmelt-1.0.3.dist-info/LICENSE
configmelt-1.0.3.dist-info/METADATA
configmelt-1.0.3.dist-info/WHEEL
configmelt-1.0.3.dist-info/top_level.txt
configmelt-1.0.3.dist-info/zip-safe
configmelt-1.0.3.dist-info/RECORD
