Metadata-Version: 2.1
Name: configmelt
Version: 1.0.3
Summary: 'config loader for json and yml files'
Home-page: https://github.com/anglisanosa/configmelt
Author: anglisanosa
Author-email: marcanglisano@gmail.com
License: ""
Project-URL: Documentation, https://anglisanosa.github.io/configmelt/
Project-URL: Bug Reports, https://github.com/anglisanosa/configmelt/issues
Project-URL: Source, https://github.com/anglisanosa/configmelt
Classifier: Programming Language :: Python :: 3
Classifier: Operating System :: OS Independent
Requires-Python: >=3.8
License-File: LICENSE
Requires-Dist: pathutility ==1.0.*
Requires-Dist: pyaml-env
Requires-Dist: jsonschema
Provides-Extra: dev
Requires-Dist: sphinx ; extra == 'dev'
Requires-Dist: sphinx-rtd-theme ; extra == 'dev'
Requires-Dist: sphinx-copybutton ; extra == 'dev'
Requires-Dist: sphinx-multiversion ; extra == 'dev'
Requires-Dist: pytest ; extra == 'dev'
Requires-Dist: pytest-cov ; extra == 'dev'
